pretix_qpaypro/__init__.py
pretix_qpaypro/payment.py
pretix_qpaypro/signals.py
pretix_qpaypro/urls.py
pretix_qpaypro/views.py
pretix_qpaypro/formfields/custom_validators.py
pretix_qpaypro/formfields/payment.py
pretix_qpaypro/formfields/settings.py
pretix_qpaypro/formfields/__pycache__/custom_validators.cpython-36.pyc
pretix_qpaypro/formfields/__pycache__/payment.cpython-36.pyc
pretix_qpaypro/formfields/__pycache__/settings.cpython-36.pyc
pretix_qpaypro/locale/django.pot
pretix_qpaypro/locale/de/LC_MESSAGES/django.mo
pretix_qpaypro/locale/de/LC_MESSAGES/django.po
pretix_qpaypro/locale/de_Informal/.gitkeep
pretix_qpaypro/locale/de_Informal/LC_MESSAGES/django.mo
pretix_qpaypro/locale/de_Informal/LC_MESSAGES/django.po
pretix_qpaypro/locale/el/LC_MESSAGES/django.mo
pretix_qpaypro/locale/el/LC_MESSAGES/django.po
pretix_qpaypro/locale/es/LC_MESSAGES/django.mo
pretix_qpaypro/locale/es/LC_MESSAGES/django.po
pretix_qpaypro/locale/nl/LC_MESSAGES/django.mo
pretix_qpaypro/locale/nl/LC_MESSAGES/django.po
pretix_qpaypro/locale/nl_BE/LC_MESSAGES/django.mo
pretix_qpaypro/locale/nl_BE/LC_MESSAGES/django.po
pretix_qpaypro/locale/nl_Informal/LC_MESSAGES/django.mo
pretix_qpaypro/locale/nl_Informal/LC_MESSAGES/django.po
pretix_qpaypro/static/pretix_qpaypro/.gitkeep
pretix_qpaypro/templates/pretix_qpaypro/.gitkeep
pretix_qpaypro/templates/pretix_qpaypro/checkout_payment_confirm.html
pretix_qpaypro/templates/pretix_qpaypro/checkout_payment_form.html
pretix_qpaypro/templates/pretix_qpaypro/onlinemetrix.html
pretix_qpaypro-1.0.5.dist-info/LICENSE
pretix_qpaypro-1.0.5.dist-info/METADATA
pretix_qpaypro-1.0.5.dist-info/WHEEL
pretix_qpaypro-1.0.5.dist-info/entry_points.txt
pretix_qpaypro-1.0.5.dist-info/top_level.txt
pretix_qpaypro-1.0.5.dist-info/RECORD
