Metadata-Version: 2.1
Name: pretix-qpaypro
Version: 1.0.5
Summary: Integration for the QPayPro payment provider.
Home-page: https://github.com/aruanoguate/pretix-qpaypro
Author: Alvaro Enrique Ruano
Author-email: alvaro.ruano90@outlook.com
License: Apache Software License
Platform: UNKNOWN
